{
  "type": "FeatureCollection",
  "features": [
    {
      "type": "Feature",
      "properties": {},
      "geometry": {
        "type": "LineString",
        "coordinates": [
          [
            77.12156653404236,
            28.59309459132636
          ],
          [
            77.11967825889587,
            28.589505375059357
          ],
          [
            77.11885213851929,
            28.587771956394466
          ],
          [
            77.11671710014343,
            28.583457127140722
          ],
          [
            77.1173796057701,
            28.58318391146778
          ],
          [
            77.11810916662216,
            28.582905984451482
          ],
          [
            77.11925178766249,
            28.582453762651703
          ],
          [
            77.12043732404709,
            28.58199211755861
          ],
          [
            77.12169528007507,
            28.581513983004424
          ],
          [
            77.12330728769302,
            28.580875681763324
          ],
          [
            77.12394565343855,
            28.5806330791686
          ],
          [
            77.12432920932768,
            28.58141270299229
          ],
          [
            77.12517410516737,
            28.583103830877402
          ],
          [
            77.12593585252762,
            28.584674812499344
          ],
          [
            77.12644815444946,
            28.585661669012115
          ],
          [
            77.12673246860504,
            28.586217507743807
          ],
          [
            77.12755054235457,
            28.587835546986316
          ],
          [
            77.12842226028442,
            28.589550123260594
          ],
          [
            77.12877094745636,
            28.59026844704222
          ],
          [
            77.12751299142838,
            28.590760672635692
          ],
          [
            77.12540477514267,
            28.591575548217424
          ],
          [
            77.12341725826263,
            28.592348025595705
          ],
          [
            77.12155044078827,
            28.59308752606038
          ]
        ]
      }
    },
    {
      "type": "Feature",
      "properties": {},
      "geometry": {
        "type": "Point",
        "coordinates": [
          77.12155848741531,
          28.593078105705008
        ]
      }
    }
  ]
}
