{
  "type": "FeatureCollection",
  "features": [
    {
      "type": "Feature",
      "properties": {},
      "geometry": {
        "type": "LineString",
        "coordinates": [
          [
            77.20612049102783,
            28.52788553595083
          ],
          [
            77.2055196762085,
            28.525906017033194
          ],
          [
            77.20564842224121,
            28.525396991874345
          ],
          [
            77.20661401748656,
            28.524096138634672
          ],
          [
            77.20627069473265,
            28.52236164267815
          ],
          [
            77.20558404922485,
            28.520004944837478
          ],
          [
            77.20991849899292,
            28.51911881282233
          ],
          [
            77.21127033233643,
            28.51870402506498
          ],
          [
            77.21410274505615,
            28.518138402766258
          ],
          [
            77.21532583236694,
            28.518006423793324
          ],
          [
            77.2159481048584,
            28.520250043867282
          ],
          [
            77.21654891967773,
            28.52262558955589
          ],
          [
            77.21654891967773,
            28.523643664179826
          ],
          [
            77.21541166305542,
            28.527451930224746
          ],
          [
            77.21485376358032,
            28.52926175100533
          ],
          [
            77.21339464187622,
            28.528865855365016
          ],
          [
            77.21221446990965,
            28.528394549092404
          ],
          [
            77.21026182174683,
            28.528187173664787
          ],
          [
            77.20601320266724,
            28.527904388333248
          ]
        ]
      }
    },
    {
      "type": "Feature",
      "properties": {},
      "geometry": {
        "type": "Point",
        "coordinates": [
          77.20605611801147,
          28.527904388333248
        ]
      }
    }
  ]
}
