{
	"type": "FeatureCollection",
	"features": [
		{
			"type": "Feature",
			"properties": {
				"marker-color": "#54bc2c",
				"marker-size": "medium",
				"marker-symbol": "harbor",
				"locality": "Cubbon Park",
				"ambassabor_name": "Anirudh",
				"ambassabor_email": "anirudhsdutt@gmail.com",
				"ambassabor_photo_profile": "http://gottila.com"
			},
			"geometry": {
				"type": "Point",
				"coordinates": [
					72.83709168434143,
					19.027920523197118
				]
			}
		},
		{
			"type": "Feature",
			"properties": {
				"stroke": "#2c34cc",
				"stroke-width": 2,
				"stroke-opacity": 1
			},
			"geometry": {
				"type": "LineString",
				"coordinates": [
					[
						72.83714532852173,
						19.02799152145505
					],
					[
						72.83572912216187,
						19.02524285246269
					],
					[
						72.83444166183472,
						19.02269699671034
					],
					[
						72.83481717109679,
						19.022341993805743
					],
					[
						72.83529996871948,
						19.021956561222105
					],
					[
						72.83582568168639,
						19.021733415633545
					],
					[
						72.83700585365295,
						19.021733415633545
					],
					[
						72.83763885498047,
						19.02172327264512
					],
					[
						72.8403639793396,
						19.02493856896694
					],
					[
						72.8407609462738,
						19.02555727815624
					],
					[
						72.8417158126831,
						19.030263449688317
					],
					[
						72.84199476242065,
						19.03155153805385
					],
					[
						72.83863663673401,
						19.03231221546826
					],
					[
						72.83861517906189,
						19.030882139047527
					],
					[
						72.83805727958679,
						19.029644758024794
					],
					[
						72.83704876899719,
						19.027900237974997
					]
				]
			}
		}
	]
}