{
  "type": "FeatureCollection",
  "features": [
    {
      "type": "Feature",
      "properties": {},
      "geometry": {
        "type": "LineString",
        "coordinates": [
          [
            88.39465498924255,
            22.646274198218595
          ],
          [
            88.39494466781616,
            22.64620488673569
          ],
          [
            88.39593172073364,
            22.645848427128186
          ],
          [
            88.39706897735596,
            22.645491966595465
          ],
          [
            88.39808821678162,
            22.645155308576122
          ],
          [
            88.39859247207642,
            22.644897863651575
          ],
          [
            88.39893579483032,
            22.64459090945699
          ],
          [
            88.39940786361693,
            22.64396709720582
          ],
          [
            88.39955806732178,
            22.643798766430393
          ],
          [
            88.39965462684631,
            22.64296701133549
          ],
          [
            88.3995795249939,
            22.642580837615018
          ],
          [
            88.39942932128906,
            22.642036231805022
          ],
          [
            88.3993649482727,
            22.6414025059625
          ],
          [
            88.39918255805969,
            22.640491519941722
          ],
          [
            88.3984100818634,
            22.64057073635727
          ],
          [
            88.39681148529053,
            22.640798483297512
          ],
          [
            88.39625358581543,
            22.640768777196282
          ],
          [
            88.3946442604065,
            22.64080838532983
          ],
          [
            88.39417219161987,
            22.64084799345195
          ],
          [
            88.39440822601318,
            22.641719369249227
          ],
          [
            88.39450478553772,
            22.642382799388496
          ],
          [
            88.3945369720459,
            22.643670042757062
          ],
          [
            88.39449405670166,
            22.644293856357407
          ],
          [
            88.3944296836853,
            22.64473943576584
          ],
          [
            88.39434385299683,
            22.64510579997427
          ],
          [
            88.39425802230835,
            22.645432556416726
          ],
          [
            88.39391469955444,
            22.64620488673569
          ],
          [
            88.39373230934143,
            22.646650459943984
          ],
          [
            88.39318513870239,
            22.64760101128982
          ],
          [
            88.39267015457153,
            22.648898107198544
          ],
          [
            88.39250922203064,
            22.649521897051102
          ],
          [
            88.39245557785034,
            22.649611009655864
          ],
          [
            88.39293837547302,
            22.649442685798334
          ],
          [
            88.39394688606262,
            22.649323868833495
          ],
          [
            88.39451551437378,
            22.64936347449987
          ],
          [
            88.3944833278656,
            22.649234756042393
          ],
          [
            88.39416146278381,
            22.649066431723632
          ],
          [
            88.39366793632507,
            22.6487891912194
          ],
          [
            88.39374303817749,
            22.648551556055967
          ],
          [
            88.39339971542358,
            22.648313920481304
          ],
          [
            88.39364647865294,
            22.64765051899216
          ],
          [
            88.39398980140685,
            22.647026720638465
          ],
          [
            88.394376039505,
            22.646412821079466
          ],
          [
            88.39456915855408,
            22.646323706399254
          ]
        ]
      }
    },
    {
      "type": "Feature",
      "properties": {},
      "geometry": {
        "type": "Point",
        "coordinates": [
          88.39950442314148,
          22.643858177315863
        ]
      }
    }
  ]
}
