{
  "type": "FeatureCollection",
  "features": [
    {
      "type": "Feature",
      "properties": {
        "stroke": "#25109a",
        "stroke-width": 2,
        "stroke-opacity": 1
      },
      "geometry": {
        "type": "LineString",
        "coordinates": [
          [
            78.56103301048279,
            25.464601422543222
          ],
          [
            78.56090694665907,
            25.4654344622148
          ],
          [
            78.56079697608948,
            25.466284447329755
          ],
          [
            78.56071382761002,
            25.46699155287791
          ],
          [
            78.56070846319199,
            25.46714411277641
          ],
          [
            78.56072723865509,
            25.467463761460248
          ],
          [
            78.56082379817963,
            25.468006193646822
          ],
          [
            78.5610356926918,
            25.469350155714174
          ],
          [
            78.56113761663437,
            25.470047557139647
          ],
          [
            78.56120735406876,
            25.47069894579117
          ],
          [
            78.561250269413,
            25.47158037314571
          ],
          [
            78.56128513813019,
            25.47202350588669
          ],
          [
            78.56127709150314,
            25.472452108132085
          ],
          [
            78.56123685836792,
            25.472626454371188
          ],
          [
            78.5612905025482,
            25.47318339205284
          ],
          [
            78.56138437986374,
            25.474219773569278
          ],
          [
            78.5614702105522,
            25.47520287488429
          ],
          [
            78.56157749891281,
            25.47514476074433
          ],
          [
            78.5618644952774,
            25.4750721180299
          ],
          [
            78.56222927570343,
            25.47505758948173
          ],
          [
            78.56264770030975,
            25.47515202501334
          ],
          [
            78.56305003166199,
            25.475282781780862
          ],
          [
            78.5636642575264,
            25.475486180914384
          ],
          [
            78.5642597079277,
            25.475677472642687
          ],
          [
            78.56495440006256,
            25.47592445644945
          ],
          [
            78.56508046388626,
            25.475629044385823
          ],
          [
            78.56533795595168,
            25.47524403904975
          ],
          [
            78.56586903333664,
            25.474442546000045
          ],
          [
            78.56661468744278,
            25.473318993880575
          ],
          [
            78.56675952672958,
            25.473115591081655
          ],
          [
            78.5673040151596,
            25.472110679348457
          ],
          [
            78.56761783361435,
            25.470916881727188
          ],
          [
            78.56799602508545,
            25.47011535984034
          ],
          [
            78.56935054063797,
            25.46902809049667
          ],
          [
            78.57064336538315,
            25.46795291916538
          ],
          [
            78.57172161340714,
            25.46705693571525
          ],
          [
            78.57215881347656,
            25.466548401599308
          ],
          [
            78.57239753007889,
            25.466286868931192
          ],
          [
            78.57179939746857,
            25.466328036148127
          ],
          [
            78.57060313224792,
            25.46644427291994
          ],
          [
            78.56990844011307,
            25.46650481286076
          ],
          [
            78.56850028038023,
            25.466427321731032
          ],
          [
            78.56689095497131,
            25.466560509579416
          ],
          [
            78.56619626283646,
            25.466453959312506
          ],
          [
            78.56515020132065,
            25.466160945591934
          ],
          [
            78.5643509030342,
            25.465996276410927
          ],
          [
            78.56402635574341,
            25.4656887318958
          ],
          [
            78.5630339384079,
            25.46526979203945
          ],
          [
            78.562331199646,
            25.46509059188664
          ],
          [
            78.56167674064636,
            25.464843585833094
          ],
          [
            78.56101423501968,
            25.464599000907867
          ]
        ]
      }
    },
    {
      "type": "Feature",
      "properties": {
        "marker-color": "#17e646",
        "marker-size": "medium",
        "marker-symbol": "harbor"
      },
      "geometry": {
        "type": "Point",
        "coordinates": [
          78.56102228164673,
          25.46458204945897
        ]
      }
    }
  ]
}