{
  "type": "FeatureCollection",
  "features": [
    {
      "type": "Feature",
      "properties": {
        "marker-color": "#21ff00",
        "marker-size": "medium",
        "marker-symbol": "harbor",
        "locality": "Cubbon Park",
        "ambassabor_name": "Anirudh",
        "ambassabor_email": "anirudhsdutt@gmail.com",
        "ambassabor_photo_profile": "http://gottila.com"
      },
      "geometry": {
        "type": "Point",
        "coordinates": [
          70.82321405410767,
          22.32212030276294
        ]
      }
    },
    {
      "type": "Feature",
      "properties": {
        "stroke": "#3600ff",
        "stroke-width": 2,
        "stroke-opacity": 1
      },
      "geometry": {
        "type": "LineString",
        "coordinates": [
          [
            70.82323551177979,
            22.322090528207063
          ],
          [
            70.82632541656494,
            22.317802925839707
          ],
          [
            70.82739830017088,
            22.31514295816939
          ],
          [
            70.82838535308836,
            22.313237278525385
          ],
          [
            70.82898616790771,
            22.31176829937895
          ],
          [
            70.82752704620361,
            22.31105365528681
          ],
          [
            70.8237075805664,
            22.310021385140573
          ],
          [
            70.8227151632309,
            22.313430825301065
          ],
          [
            70.82228064537048,
            22.314874973541347
          ],
          [
            70.8222109079361,
            22.31544568092671
          ],
          [
            70.82158327102661,
            22.31711808826234
          ],
          [
            70.82131505012511,
            22.317951803129294
          ],
          [
            70.82080006599426,
            22.31873588756724
          ],
          [
            70.82031726837158,
            22.319331391792186
          ],
          [
            70.8202314376831,
            22.319500117527316
          ],
          [
            70.82187294960022,
            22.321038489821404
          ],
          [
            70.82242012023926,
            22.32147518596314
          ],
          [
            70.82273125648499,
            22.32172330816214
          ],
          [
            70.82306385040283,
            22.32215007731248
          ],
          [
            70.8231496810913,
            22.32226917544707
          ]
        ]
      }
    }
  ]
}