{
  "type": "FeatureCollection",
  "features": [
    {
      "type": "Feature",
      "properties": {
        "marker-color": "#01ff00",
        "marker-size": "medium",
        "marker-symbol": "harbor",
       "locality": "Cubbon Park",
        "ambassabor_name": "Anirudh",
        "ambassabor_email": "anirudhsdutt@gmail.com",
        "ambassabor_photo_profile": "http://gottila.com"
      },
      "geometry": {
        "type": "Point",
        "coordinates": [
          77.5404401,
          12.907673,
          0
        ]
      }
    },
    {
      "type": "Feature",
      "properties": {},
      "geometry": {
        "type": "LineString",
        "coordinates": [
          [
            77.54916429519653,
            12.90909746978022
          ],
          [
            77.54742622375488,
            12.907717053185303
          ],
          [
            77.54656791687012,
            12.907110504089351
          ],
          [
            77.54446506500244,
            12.90660853131093
          ],
          [
            77.5434136390686,
            12.906190219892428
          ],
          [
            77.5426197052002,
            12.905750992149823
          ],
          [
            77.54182577133179,
            12.905813739017422
          ],
          [
            77.54178285598755,
            12.906064726330419
          ],
          [
            77.54150390625,
            12.906964095466414
          ],
          [
            77.5411605834961,
            12.907256912626554
          ],
          [
            77.54032373428345,
            12.907821630466923
          ],
          [
            77.53974437713623,
            12.908093531194389
          ],
          [
            77.5389289855957,
            12.90851183942843
          ],
          [
            77.53841400146483,
            12.908449093237946
          ],
          [
            77.53819942474365,
            12.908428177837628
          ],
          [
            77.53867149353027,
            12.908888316240635
          ],
          [
            77.53882169723511,
            12.909306623144797
          ],
          [
            77.53916501998901,
            12.909724929348982
          ],
          [
            77.53942251205444,
            12.910143234853154
          ],
          [
            77.5394868850708,
            12.91093801338252
          ],
          [
            77.5394868850708,
            12.911565468331096
          ],
          [
            77.5395941734314,
            12.91221383678976
          ],
          [
            77.5399374961853,
            12.912004685857836
          ],
          [
            77.54047393798828,
            12.911900110326247
          ],
          [
            77.54092454910278,
            12.911711874259097
          ],
          [
            77.54234075546263,
            12.911272656217783
          ],
          [
            77.54245609045029,
            12.911246512262403
          ],
          [
            77.54265993833542,
            12.911845208154636
          ],
          [
            77.54276722669601,
            12.912239980643946
          ],
          [
            77.54268139600754,
            12.912263510110364
          ],
          [
            77.54267066717148,
            12.912305340267435
          ],
          [
            77.54300594329833,
            12.913421679997427
          ],
          [
            77.5429978966713,
            12.913432137488885
          ],
          [
            77.54301398992538,
            12.913432137488885
          ],
          [
            77.54342168569565,
            12.91331449068474
          ],
          [
            77.5437194108963,
            12.913991612643942
          ],
          [
            77.5437381863594,
            12.914002070111557
          ],
          [
            77.54419952630997,
            12.913876580471376
          ],
          [
            77.54450261592865,
            12.913795535045253
          ],
          [
            77.54472255706787,
            12.913787691938104
          ],
          [
            77.54483252763748,
            12.913764162615193
          ],
          [
            77.54512220621108,
            12.913701417743239
          ],
          [
            77.54519194364548,
            12.91365958781985
          ],
          [
            77.54513829946518,
            12.9134661243331
          ],
          [
            77.54499077796936,
            12.912924948649053
          ],
          [
            77.54551112651825,
            12.91274717087392
          ],
          [
            77.54620313644409,
            12.912572007354145
          ],
          [
            77.54639089107512,
            12.912532791623951
          ],
          [
            77.54630506038666,
            12.912339327264903
          ],
          [
            77.54622995853423,
            12.912070045542862
          ],
          [
            77.54617899656296,
            12.911753704508493
          ],
          [
            77.54606634378433,
            12.911155008397069
          ],
          [
            77.5459536910057,
            12.910483107559859
          ],
          [
            77.54624336957932,
            12.910556310851584
          ],
          [
            77.54680931568146,
            12.910728861382973
          ],
          [
            77.54675567150116,
            12.9098242769696
          ],
          [
            77.54761934280394,
            12.909677869935946
          ],
          [
            77.54803240299225,
            12.909562835777924
          ],
          [
            77.54882633686066,
            12.909301394312811
          ],
          [
            77.54920721054077,
            12.909144529302502
          ]
        ]
      }
    }
  ]
}
