{
  "type": "FeatureCollection",
  "features": [
    {
      "type": "Feature",
      "properties": {
        "marker-color": "#1dfd1f",
        "marker-size": "medium",
        "marker-symbol": "harbor",
        "locality": "Cubbon Park",
        "ambassabor_name": "Anirudh",
        "ambassabor_email": "anirudhsdutt@gmail.com",
        "ambassabor_photo_profile": "http://gottila.com"
      },
      "geometry": {
        "type": "Point",
        "coordinates": [
          77.5661269,
          12.8828322,
          0
        ]
      }
    },
    {
      "type": "Feature",
      "properties": {},
      "geometry": {
        "type": "LineString",
        "coordinates": [
          [
            77.57066488265991,
            12.886330080409605
          ],
          [
            77.56894826889038,
            12.886581087264972
          ],
          [
            77.56805777549744,
            12.886612463104207
          ],
          [
            77.56733894348143,
            12.886612463104207
          ],
          [
            77.56697416305542,
            12.88659154587848
          ],
          [
            77.56619095802306,
            12.886675214770868
          ],
          [
            77.56636261940002,
            12.886466042487498
          ],
          [
            77.56654500961304,
            12.886277787283081
          ],
          [
            77.56671667098999,
            12.88573393811988
          ],
          [
            77.56687760353088,
            12.885420178450065
          ],
          [
            77.56682395935059,
            12.885022748970728
          ],
          [
            77.56674885749817,
            12.884499814484487
          ],
          [
            77.56670594215393,
            12.884081466109429
          ],
          [
            77.56658792495728,
            12.883746786906316
          ],
          [
            77.56638407707214,
            12.88351669469479
          ],
          [
            77.56616950035095,
            12.88317155598122
          ],
          [
            77.56606221199036,
            12.882805499250228
          ],
          [
            77.565997838974,
            12.882418524410129
          ],
          [
            77.56605148315428,
            12.882115219387872
          ],
          [
            77.56619095802306,
            12.881811913998414
          ],
          [
            77.56685614585875,
            12.881508608241742
          ],
          [
            77.56696343421936,
            12.881320349311558
          ],
          [
            77.5670599937439,
            12.880818324806123
          ],
          [
            77.56730675697327,
            12.879877026147248
          ],
          [
            77.56737112998962,
            12.879406375491762
          ],
          [
            77.56728529930115,
            12.879061231115898
          ],
          [
            77.5674569606781,
            12.87900893647202
          ],
          [
            77.56895899772644,
            12.88174916111337
          ],
          [
            77.57024645805359,
            12.884625318860765
          ],
          [
            77.57068634033203,
            12.886267328656471
          ]
        ]
      }
    }
  ]
}
