{
  "type": "FeatureCollection",
  "features": [
    {
      "type": "Feature",
      "properties": {
        "stroke": "#0003ff",
        "stroke-width": 2,
        "stroke-opacity": 1
      },
      "geometry": {
        "type": "LineString",
        "coordinates": [
          [
            77.95469284057617,
            27.17956147975083
          ],
          [
            77.95520782470703,
            27.186662102327727
          ],
          [
            77.94010162353516,
            27.18246286400776
          ],
          [
            77.94010162353516,
            27.181775700870602
          ],
          [
            77.95061588287354,
            27.180210480148347
          ],
          [
            77.95267581939697,
            27.179790539145696
          ],
          [
            77.95443534851074,
            27.179637832934706
          ]
        ]
      }
    },
    {
      "type": "Feature",
      "properties": {
        "marker-color": "#3dff00",
        "marker-size": "medium",
        "marker-symbol": "harbor"
      },
      "geometry": {
        "type": "Point",
        "coordinates": [
          77.95456409454346,
          27.17971418606632
        ]
      }
    }
  ]
}
