{
  "type": "FeatureCollection",
  "features": [
    {
      "type": "Feature",
      "properties": {},
      "geometry": {
        "type": "LineString",
        "coordinates": [
          [
            76.76809430122374,
            30.725964704938438
          ],
          [
            76.76768660545349,
            30.725854032104586
          ],
          [
            76.76407098770142,
            30.723612879881426
          ],
          [
            76.7629873752594,
            30.7228934866403
          ],
          [
            76.76296591758728,
            30.722727472053084
          ],
          [
            76.7631483078003,
            30.72245078043913
          ],
          [
            76.76403880119324,
            30.721353229214998
          ],
          [
            76.76134586334227,
            30.719674597293494
          ],
          [
            76.76075577735901,
            30.71932411001757
          ],
          [
            76.76064848899841,
            30.719130419134327
          ],
          [
            76.76063776016235,
            30.718909057648453
          ],
          [
            76.76211833953857,
            30.717018240914893
          ],
          [
            76.76234364509583,
            30.716907557811105
          ],
          [
            76.76261186599731,
            30.716926005003884
          ],
          [
            76.76604509353638,
            30.71905663202884
          ],
          [
            76.7674720287323,
            30.71738718367675
          ],
          [
            76.76770806312561,
            30.71722115960858
          ],
          [
            76.76790118217468,
            30.71722115960858
          ],
          [
            76.76884531974792,
            30.717756125026998
          ],
          [
            76.77267551422119,
            30.720191102535882
          ],
          [
            76.77282571792603,
            30.720375568023332
          ],
          [
            76.77290081977844,
            30.72060614938638
          ],
          [
            76.77286863327025,
            30.720956632002128
          ],
          [
            76.77138805389404,
            30.722764364208277
          ],
          [
            76.76939249038696,
            30.725042427440606
          ],
          [
            76.76873803138733,
            30.725807918386316
          ],
          [
            76.76844835281372,
            30.725909368537387
          ],
          [
            76.76804065704346,
            30.726010818581695
          ]
        ]
      }
    },
    {
      "type": "Feature",
      "properties": {},
      "geometry": {
        "type": "Point",
        "coordinates": [
          76.76807284355164,
          30.72594625947494
        ]
      }
    }
  ]
}
