{
  "type": "FeatureCollection",
  "features": [
    {
      "type": "Feature",
      "properties": {},
      "geometry": {
        "type": "LineString",
        "coordinates": [
          [
            76.73323631286621,
            30.686363392380905
          ],
          [
            76.73846125602722,
            30.680015339694624
          ],
          [
            76.7406177520752,
            30.677459392511366
          ],
          [
            76.74275279045105,
            30.678825033357008
          ],
          [
            76.74161553382874,
            30.680199881999286
          ],
          [
            76.74434065818787,
            30.681897654655955
          ],
          [
            76.74288153648376,
            30.68369689201237
          ],
          [
            76.74105763435364,
            30.68585593258654
          ],
          [
            76.74084305763245,
            30.686031237180686
          ],
          [
            76.73953413963318,
            30.686686319952273
          ],
          [
            76.73919081687927,
            30.686926208306087
          ],
          [
            76.73848271369934,
            30.687793491996924
          ],
          [
            76.73740983009338,
            30.68904827163166
          ],
          [
            76.73317193984985,
            30.68638184541407
          ]
        ]
      }
    },
    {
      "type": "Feature",
      "properties": {},
      "geometry": {
        "type": "Point",
        "coordinates": [
          76.73318266868591,
          30.686326486303987
        ]
      }
    }
  ]
}
