{
  "type": "FeatureCollection",
  "features": [
    {
      "type": "Feature",
      "properties": {
        "marker-color": "#00ff0d",
        "marker-size": "medium",
        "marker-symbol": "harbor",
        "locality": "Cubbon Park",
        "ambassabor_name": "Anirudh",
        "ambassabor_email": "anirudhsdutt@gmail.com",
        "ambassabor_photo_profile": "http://gottila.com"
      },
      "geometry": {
        "type": "Point",
        "coordinates": [
          72.84853935241699,
          21.144030897194632
        ]
      }
    },
    {
      "type": "Feature",
      "properties": {
        "stroke": "#3100ff",
        "stroke-width": 2,
        "stroke-opacity": 1
      },
      "geometry": {
        "type": "LineString",
        "coordinates": [
          [
            72.84864664077759,
            21.144110949448343
          ],
          [
            72.85253047943115,
            21.13418414015028
          ],
          [
            72.84815311431883,
            21.133163402300013
          ],
          [
            72.84555673599243,
            21.140328433197165
          ],
          [
            72.84650087356566,
            21.14096886601987
          ],
          [
            72.84547090530396,
            21.14279008173053
          ],
          [
            72.84834623336792,
            21.14409093638897
          ]
        ]
      }
    },
    {
      "type": "Feature",
      "properties": {},
      "geometry": {
        "type": "LineString",
        "coordinates": [
          [
            72.78839349746704,
            21.191214192855753
          ],
          [
            72.79032468795776,
            21.18781301674834
          ],
          [
            72.79041051864624,
            21.18711276489293
          ],
          [
            72.79309272766113,
            21.18587231060608
          ],
          [
            72.7940583229065,
            21.18721280107539
          ],
          [
            72.79620409011841,
            21.18995376613248
          ],
          [
            72.79543161392212,
            21.190113820915407
          ],
          [
            72.79427289962769,
            21.190533963895874
          ],
          [
            72.79388666152953,
            21.19101412583962
          ],
          [
            72.79435873031616,
            21.19127421290777
          ],
          [
            72.79371500015259,
            21.192194517319653
          ],
          [
            72.79380083084106,
            21.192614654384837
          ],
          [
            72.79374182224274,
            21.194482749371538
          ],
          [
            72.79350578784943,
            21.19524298474663
          ],
          [
            72.79300689697266,
            21.195180465537728
          ],
          [
            72.79095768928528,
            21.194960397711988
          ],
          [
            72.78936982154846,
            21.194645300027208
          ],
          [
            72.78822183609009,
            21.194455240781334
          ],
          [
            72.78651595115662,
            21.194115134152277
          ],
          [
            72.7868378162384,
            21.19362497910391
          ],
          [
            72.7883505821228,
            21.19126420956745
          ]
        ]
      }
    },
    {
      "type": "Feature",
      "properties": {},
      "geometry": {
        "type": "Point",
        "coordinates": [
          72.78835594654083,
          21.191214192855753
        ]
      }
    },
    {
      "type": "Feature",
      "properties": {},
      "geometry": {
        "type": "LineString",
        "coordinates": [
          [
            72.80279159545898,
            21.18141059059212
          ],
          [
            72.80163288116455,
            21.18061026782764
          ],
          [
            72.79918670654297,
            21.17892957592251
          ],
          [
            72.79682636260986,
            21.176928727319954
          ],
          [
            72.79510974884033,
            21.175408064277665
          ],
          [
            72.79390811920166,
            21.174087475793623
          ],
          [
            72.79438018798828,
            21.173847367529774
          ],
          [
            72.79781341552734,
            21.174287565715755
          ],
          [
            72.80158996582031,
            21.174527673265036
          ],
          [
            72.80519485473633,
            21.174967869426393
          ],
          [
            72.8050661087036,
            21.175928292867408
          ],
          [
            72.80467987060547,
            21.177008761783807
          ],
          [
            72.80420780181885,
            21.178129239729984
          ],
          [
            72.80279159545898,
            21.181170494217614
          ]
        ]
      }
    },
    {
      "type": "Feature",
      "properties": {},
      "geometry": {
        "type": "Point",
        "coordinates": [
          72.80274868011473,
          21.181210510307103
        ]
      }
    },
    {
      "type": "Feature",
      "properties": {},
      "geometry": {
        "type": "LineString",
        "coordinates": [
          [
            72.84800291061401,
            21.173487204403223
          ],
          [
            72.84834623336792,
            21.171826440863935
          ],
          [
            72.84896850585938,
            21.16896508163578
          ],
          [
            72.84688711166382,
            21.168584896874137
          ],
          [
            72.84051418304443,
            21.170305725367164
          ],
          [
            72.84006357192993,
            21.17034574439629
          ],
          [
            72.83965587615967,
            21.171946496684736
          ],
          [
            72.83975780010223,
            21.171961503655503
          ],
          [
            72.84073948860167,
            21.172096566323752
          ],
          [
            72.84226298332214,
            21.172386700527476
          ],
          [
            72.84326612949371,
            21.172551776630772
          ],
          [
            72.84596979618073,
            21.173107031262692
          ],
          [
            72.84793853759766,
            21.17350721348881
          ]
        ]
      }
    },
    {
      "type": "Feature",
      "properties": {},
      "geometry": {
        "type": "Point",
        "coordinates": [
          72.84794926643372,
          21.17343718167739
        ]
      }
    },
    {
      "type": "Feature",
      "properties": {
        "marker-color": "#0bff00",
        "marker-size": "medium",
        "marker-symbol": "harbor",
        "locality": "Cubbon Park",
        "ambassabor_name": "Anirudh",
        "ambassabor_email": "anirudhsdutt@gmail.com",
        "ambassabor_photo_profile": "http://gottila.com"
      },
      "geometry": {
        "type": "Point",
        "coordinates": [
          72.79407978057861,
          21.20333774842867
        ]
      }
    },
    {
      "type": "Feature",
      "properties": {
        "stroke": "#000cff",
        "stroke-width": 2,
        "stroke-opacity": 1
      },
      "geometry": {
        "type": "LineString",
        "coordinates": [
          [
            72.79399394989014,
            21.20335775347368
          ],
          [
            72.78942346572876,
            21.202757600944615
          ],
          [
            72.7898097038269,
            21.2002369336927
          ],
          [
            72.79111862182617,
            21.198116339038986
          ],
          [
            72.79332876205444,
            21.195815659469115
          ],
          [
            72.79380083084106,
            21.19631581024936
          ],
          [
            72.79455184936522,
            21.196755941535415
          ],
          [
            72.79560327529907,
            21.197876269801547
          ],
          [
            72.79558181762695,
            21.198336402163918
          ],
          [
            72.79480934143066,
            21.19975680172007
          ],
          [
            72.7947449684143,
            21.200316955536415
          ],
          [
            72.79468059539795,
            21.201177187618455
          ],
          [
            72.79455184936522,
            21.201977399010975
          ],
          [
            72.7942943572998,
            21.202477528929794
          ],
          [
            72.79397249221802,
            21.20287763164552
          ],
          [
            72.79397249221802,
            21.203237723162964
          ]
        ]
      }
    },
    {
      "type": "Feature",
      "properties": {
        "marker-color": "#2bff00",
        "marker-size": "medium",
        "marker-symbol": "harbor",
        "locality": "Cubbon Park",
        "ambassabor_name": "Anirudh",
        "ambassabor_email": "anirudhsdutt@gmail.com",
        "ambassabor_photo_profile": "http://gottila.com"
      },
      "geometry": {
        "type": "Point",
        "coordinates": [
          72.81094551086426,
          21.17562816121202
        ]
      }
    },
    {
      "type": "Feature",
      "properties": {
        "stroke": "#1400ff",
        "stroke-width": 2,
        "stroke-opacity": 1
      },
      "geometry": {
        "type": "LineString",
        "coordinates": [
          [
            72.81092405319214,
            21.175608152413343
          ],
          [
            72.81182527542114,
            21.167924573650506
          ],
          [
            72.81229734420775,
            21.164042613905508
          ],
          [
            72.81249046325684,
            21.16380248933984
          ],
          [
            72.81527996063232,
            21.169725448228295
          ],
          [
            72.81836986541748,
            21.176428510939587
          ],
          [
            72.81111717224121,
            21.17566817880127
          ]
        ]
      }
    },
    {
      "type": "Feature",
      "properties": {
        "marker-color": "#18ff00",
        "marker-size": "medium",
        "marker-symbol": "harbor",
        "locality": "Cubbon Park",
        "ambassabor_name": "Anirudh",
        "ambassabor_email": "anirudhsdutt@gmail.com",
        "ambassabor_photo_profile": "http://gottila.com"
      },
      "geometry": {
        "type": "Point",
        "coordinates": [
          72.82034397125244,
          21.23710240458913
        ]
      }
    },
    {
      "type": "Feature",
      "properties": {
        "stroke": "#4d00ff",
        "stroke-width": 2,
        "stroke-opacity": 1
      },
      "geometry": {
        "type": "LineString",
        "coordinates": [
          [
            72.82048344612122,
            21.236982401723726
          ],
          [
            72.82637357711792,
            21.235482357665013
          ],
          [
            72.83236026763915,
            21.233862292940657
          ],
          [
            72.8369951248169,
            21.232642232448146
          ],
          [
            72.83697366714476,
            21.232502224860735
          ],
          [
            72.83557891845703,
            21.23188218966158
          ],
          [
            72.833411693573,
            21.23150216679937
          ],
          [
            72.82959222793579,
            21.2303620923373
          ],
          [
            72.82778978347778,
            21.229862056898142
          ],
          [
            72.8264594078064,
            21.229802052531525
          ],
          [
            72.82545089721678,
            21.229962064121604
          ],
          [
            72.82424926757812,
            21.230182079774504
          ],
          [
            72.82163143157959,
            21.230522103319778
          ],
          [
            72.82034397125244,
            21.236962401236667
          ],
          [
            72.82042980194092,
            21.237222407356853
          ]
        ]
      }
    },
    {
      "type": "Feature",
      "properties": {
        "marker-color": "#1dff00",
        "marker-size": "medium",
        "marker-symbol": "harbor",
        "locality": "Cubbon Park",
        "ambassabor_name": "Anirudh",
        "ambassabor_email": "anirudhsdutt@gmail.com",
        "ambassabor_photo_profile": "http://gottila.com"
      },
      "geometry": {
        "type": "Point",
        "coordinates": [
          72.81699657440186,
          21.19185440548726
        ]
      }
    },
    {
      "type": "Feature",
      "properties": {
        "stroke": "#0034ff",
        "stroke-width": 2,
        "stroke-opacity": 1
      },
      "geometry": {
        "type": "LineString",
        "coordinates": [
          [
            72.81673908233643,
            21.1919744450469
          ],
          [
            72.81630992889404,
            21.192214523873645
          ],
          [
            72.81566619873047,
            21.19205447136582
          ],
          [
            72.8149366378784,
            21.191894418684644
          ],
          [
            72.81433582305908,
            21.191774379059993
          ],
          [
            72.81386375427246,
            21.191414259601032
          ],
          [
            72.81330585479736,
            21.19101412583962
          ],
          [
            72.81266212463379,
            21.190654004528074
          ],
          [
            72.8130054473877,
            21.190133827751083
          ],
          [
            72.81330585479736,
            21.18965366294732
          ],
          [
            72.81266212463379,
            21.189733690522942
          ],
          [
            72.81214714050293,
            21.18965366294732
          ],
          [
            72.81163215637206,
            21.189253524419183
          ],
          [
            72.81090259552002,
            21.188693328659873
          ],
          [
            72.81034469604492,
            21.18837321584413
          ],
          [
            72.810001373291,
            21.18805310233509
          ],
          [
            72.81013011932373,
            21.187332844404956
          ],
          [
            72.81034469604492,
            21.18649253905069
          ],
          [
            72.81073093414307,
            21.18601236241782
          ],
          [
            72.81116008758545,
            21.18601236241782
          ],
          [
            72.81167507171631,
            21.1862124362044
          ],
          [
            72.8124475479126,
            21.18641250972019
          ],
          [
            72.81283378601074,
            21.1867326267822
          ],
          [
            72.81399250030518,
            21.1872528155294
          ],
          [
            72.81450748443604,
            21.187332844404956
          ],
          [
            72.81497955322266,
            21.187652959473855
          ],
          [
            72.81609535217285,
            21.187692973808733
          ],
          [
            72.81652450561523,
            21.187172786610528
          ],
          [
            72.8173828125,
            21.18721280107539
          ],
          [
            72.818284034729,
            21.187092757648323
          ],
          [
            72.81871318817139,
            21.187132772134852
          ],
          [
            72.81909942626953,
            21.187652959473855
          ],
          [
            72.8184986114502,
            21.188533272338663
          ],
          [
            72.81841278076172,
            21.18909346870461
          ],
          [
            72.81789779663085,
            21.189853731805133
          ],
          [
            72.81751155853271,
            21.190493950330154
          ],
          [
            72.8170394897461,
            21.191894418684644
          ]
        ]
      }
    },
    {
      "type": "Feature",
      "properties": {
        "marker-color": "#50ff00",
        "marker-size": "medium",
        "marker-symbol": "harbor",
        "locality": "Cubbon Park",
        "ambassabor_name": "Anirudh",
        "ambassabor_email": "anirudhsdutt@gmail.com",
        "ambassabor_photo_profile": "http://gottila.com"
      },
      "geometry": {
        "type": "Point",
        "coordinates": [
          72.82969951629639,
          21.19185440548726
        ]
      }
    },
    {
      "type": "Feature",
      "properties": {
        "stroke": "#0f00ff",
        "stroke-width": 2,
        "stroke-opacity": 1
      },
      "geometry": {
        "type": "LineString",
        "coordinates": [
          [
            72.82957077026367,
            21.191894418684644
          ],
          [
            72.82785415649414,
            21.19045393675358
          ],
          [
            72.82665252685547,
            21.18909346870461
          ],
          [
            72.8266954421997,
            21.18851326528633
          ],
          [
            72.82738208770752,
            21.187192793844307
          ],
          [
            72.82841205596922,
            21.186352487693885
          ],
          [
            72.82894849777222,
            21.186132406722262
          ],
          [
            72.82918453216553,
            21.184871936663576
          ],
          [
            72.82950639724731,
            21.184211686153187
          ],
          [
            72.83019304275513,
            21.184011609658786
          ],
          [
            72.83032178878784,
            21.18409164028904
          ],
          [
            72.83019304275513,
            21.184631845910065
          ],
          [
            72.83066511154175,
            21.184771898897004
          ],
          [
            72.83133029937744,
            21.18503199694929
          ],
          [
            72.83201694488524,
            21.18525207955919
          ],
          [
            72.83291816711426,
            21.185712251230203
          ],
          [
            72.83324003219604,
            21.185812288360445
          ],
          [
            72.83315420150757,
            21.186152414096853
          ],
          [
            72.83293962478638,
            21.186972714123776
          ],
          [
            72.83276796340942,
            21.187472894832897
          ],
          [
            72.83253192901611,
            21.187953066721334
          ],
          [
            72.832510471344,
            21.18855327938829
          ],
          [
            72.83242464065552,
            21.189153489617883
          ],
          [
            72.83244609832764,
            21.18965366294732
          ],
          [
            72.83236026763915,
            21.190033793545602
          ],
          [
            72.83197402954102,
            21.191294219586354
          ],
          [
            72.8318452835083,
            21.191574312802242
          ],
          [
            72.83186674118042,
            21.191794385670878
          ],
          [
            72.83171653747559,
            21.19245460231038
          ],
          [
            72.83105134963988,
            21.192154504203522
          ],
          [
            72.83057928085327,
            21.192214523873645
          ],
          [
            72.83025741577148,
            21.192094484509038
          ],
          [
            72.82984972000122,
            21.191894418684644
          ],
          [
            72.82969951629639,
            21.191894418684644
          ]
        ]
      }
    },
    {
      "type": "Feature",
      "properties": {
        "marker-color": "#38ff00",
        "marker-size": "medium",
        "marker-symbol": "harbor",
        "locality": "Cubbon Park",
        "ambassabor_name": "Anirudh",
        "ambassabor_email": "anirudhsdutt@gmail.com",
        "ambassabor_photo_profile": "http://gottila.com"
      },
      "geometry": {
        "type": "Point",
        "coordinates": [
          72.70391464233398,
          21.094910690803513
        ]
      }
    },
    {
      "type": "Feature",
      "properties": {
        "stroke": "#3d00ff",
        "stroke-width": 2,
        "stroke-opacity": 1
      },
      "geometry": {
        "type": "LineString",
        "coordinates": [
          [
            72.70400047302246,
            21.09483061199344
          ],
          [
            72.71198272705078,
            21.08373927976836
          ],
          [
            72.71550178527832,
            21.08658226333365
          ],
          [
            72.71266937255858,
            21.088984742250464
          ],
          [
            72.71078109741211,
            21.09146726298481
          ],
          [
            72.70794868469238,
            21.093629424661398
          ],
          [
            72.7060604095459,
            21.096512257937956
          ],
          [
            72.70434379577637,
            21.095231005612046
          ]
        ]
      }
    },
    {
      "type": "Feature",
      "properties": {
        "marker-color": "#04ff00",
        "marker-size": "medium",
        "marker-symbol": "harbor",
        "locality": "Cubbon Park",
        "ambassabor_name": "Anirudh",
        "ambassabor_email": "anirudhsdutt@gmail.com",
        "ambassabor_photo_profile": "http://gottila.com"
      },
      "geometry": {
        "type": "Point",
        "coordinates": [
          72.82493591308594,
          21.14971449970736
        ]
      }
    },
    {
      "type": "Feature",
      "properties": {
        "stroke": "#0002ff",
        "stroke-width": 2,
        "stroke-opacity": 1
      },
      "geometry": {
        "type": "LineString",
        "coordinates": [
          [
            72.8248929977417,
            21.14971449970736
          ],
          [
            72.82613754272461,
            21.13926771024567
          ],
          [
            72.82811164855957,
            21.13978806584991
          ],
          [
            72.82793998718262,
            21.14114898725251
          ],
          [
            72.82824039459229,
            21.141949523415033
          ],
          [
            72.82811164855957,
            21.14254992269844
          ],
          [
            72.82755374908447,
            21.14479139185848
          ],
          [
            72.82763957977295,
            21.146912751075686
          ],
          [
            72.82729625701904,
            21.14991462258158
          ],
          [
            72.82515048980713,
            21.1497945488895
          ]
        ]
      }
    },
    {
      "type": "Feature",
      "properties": {
        "marker-color": "#01ff00",
        "marker-size": "medium",
        "marker-symbol": "harbor",
        "locality": "Cubbon Park",
        "ambassabor_name": "Anirudh",
        "ambassabor_email": "anirudhsdutt@gmail.com",
        "ambassabor_photo_profile": "http://gottila.com"
      },
      "geometry": {
        "type": "Point",
        "coordinates": [
          72.85055637359619,
          21.221061155714285
        ]
      }
    },
    {
      "type": "Feature",
      "properties": {
        "stroke": "#2300ff",
        "stroke-width": 2,
        "stroke-opacity": 1
      },
      "geometry": {
        "type": "LineString",
        "coordinates": [
          [
            72.85064220428467,
            21.22118117153397
          ],
          [
            72.85111427307127,
            21.210179315803153
          ],
          [
            72.85420417785645,
            21.211339550176643
          ],
          [
            72.85776615142822,
            21.21273982089794
          ],
          [
            72.86111354827881,
            21.214140078336882
          ],
          [
            72.8630018234253,
            21.215820369729915
          ],
          [
            72.86038398742676,
            21.216740521196492
          ],
          [
            72.85742282867432,
            21.21750064199414
          ],
          [
            72.85454750061035,
            21.218140740681978
          ],
          [
            72.85373210906981,
            21.218220752822727
          ],
          [
            72.85162925720215,
            21.220021014521226
          ],
          [
            72.85150051116943,
            21.22086112913118
          ],
          [
            72.85081386566162,
            21.220981145113573
          ]
        ]
      }
    },
    {
      "type": "Feature",
      "properties": {
        "marker-color": "#1bff00",
        "marker-size": "medium",
        "marker-symbol": "harbor",
        "locality": "Cubbon Park",
        "ambassabor_name": "Anirudh",
        "ambassabor_email": "anirudhsdutt@gmail.com",
        "ambassabor_photo_profile": "http://gottila.com"
      },
      "geometry": {
        "type": "Point",
        "coordinates": [
          72.84587860107422,
          21.205218210815396
        ]
      }
    },
    {
      "type": "Feature",
      "properties": {
        "stroke": "#0500ff",
        "stroke-width": 2,
        "stroke-opacity": 1
      },
      "geometry": {
        "type": "LineString",
        "coordinates": [
          [
            72.84613609313965,
            21.205338239516482
          ],
          [
            72.84639358520508,
            21.20105715553566
          ],
          [
            72.84635066986084,
            21.200577026229087
          ],
          [
            72.84673690795898,
            21.200577026229087
          ],
          [
            72.84918308258057,
            21.200577026229087
          ],
          [
            72.8492259979248,
            21.20465807558705
          ],
          [
            72.84909725189209,
            21.206058409674323
          ],
          [
            72.849440574646,
            21.206458502688875
          ],
          [
            72.84862518310547,
            21.209099089397064
          ],
          [
            72.843861579895,
            21.207818810829824
          ],
          [
            72.84484863281249,
            21.204778104743404
          ],
          [
            72.84583568572997,
            21.20541825859635
          ]
        ]
      }
    }
  ]
}